py_calling_agent/__init__.py
py_calling_agent/agent.py
py_calling_agent/constant.py
py_calling_agent/models.py
py_calling_agent/prompts.py
py_calling_agent/python_runtime.py
py_calling_agent/security_checker.py
py_calling_agent/streaming_text_parser.py
py_calling_agent/utils.py
py_calling_agent-0.4.4.dist-info/METADATA
py_calling_agent-0.4.4.dist-info/WHEEL
py_calling_agent-0.4.4.dist-info/licenses/LICENSE
py_calling_agent-0.4.4.dist-info/RECORD
