Metadata-Version: 2.4
Name: py-calling-agent
Version: 0.4.4
Summary: A Python agent framework that enables function-calling through LLM code generation
Project-URL: Homepage, https://github.com/acodercat/py-calling-agent
Project-URL: Repository, https://github.com/acodercat/py-calling-agent
Author-email: Ram <codermao@gmail.com>, Cooper <cooperimmaculate@gmail.com>
License-File: LICENSE
Keywords: agent,function-calling,llm
Classifier: Development Status :: 3 - Alpha
Classifier: Intended Audience :: Developers
Classifier: License :: OSI Approved :: MIT License
Classifier: Programming Language :: Python :: 3.11
Classifier: Programming Language :: Python :: 3.12
Classifier: Topic :: Software Development :: Libraries :: Python Modules
Requires-Python: >=3.11
Requires-Dist: ipython>=9.0.2
Requires-Dist: rich>=13.9.4
Provides-Extra: all
Requires-Dist: litellm>=1.73.0; extra == 'all'
Requires-Dist: openai>=1.91.0; extra == 'all'
Provides-Extra: litellm
Requires-Dist: litellm>=1.73.0; extra == 'litellm'
Provides-Extra: openai
Requires-Dist: openai>=1.91.0; extra == 'openai'
